[
    {
        "age": null,
        "album": "",
        "author": "Joe Tilleli",
        "bookmarked": false,
        "comments": [],
        "date_created": "2026-01-01T14:42:28.045809+00:00",
        "date_dead_since": null,
        "date_published": "2026-01-01T14:05:23+00:00",
        "description": "<p><img width=\"1920\" height=\"1280\" src=\"https://kotaku.com/app/uploads/2025/12/AppleWatch-Series11.jpg\" class=\"attachment-full size-full wp-post-image\" alt=\"Applewatch Series11\" style=\"max-width: 100%; height: auto; margin: auto;\" decoding=\"async\" fetchpriority=\"high\" srcset=\"https://kotaku.com/app/uploads/2025/12/AppleWatch-Series11.jpg 1920w, https://kotaku.com/app/uploads/2025/12/AppleWatch-Series11-336x224.jpg 336w, https://kotaku.com/app/uploads/2025/12/AppleWatch-Series11-1280x853.jpg 1280w, https://kotaku.com/app/uploads/2025/12/AppleWatch-Series11-768x512.jpg 768w, https://kotaku.com/app/uploads/2025/12/AppleWatch-Series11-672x448.jpg 672w, https://kotaku.com/app/uploads/2025/12/AppleWatch-Series11-960x640.jpg 960w, https://kotaku.com/app/uploads/2025/12/AppleWatch-Series11-1600x1067.jpg 1600w\" sizes=\"(max-width: 1920px) 100vw, 1920px\"></p>\n<p>Save $100 on the Apple Watch Series 11 for a limited time in either size.</p>\n<p>The post <a href=\"https://kotaku.com/apple-watch-serie",
        "id": 4450165,
        "language": "en",
        "link": "https://kotaku.com/apple-watch-series-11-crashes-to-record-low-to-wind-down-its-2025-smartwatch-lineup-2000656173",
        "manual_status_code": 0,
        "page_rating": 32,
        "page_rating_contents": 100,
        "page_rating_visits": 0,
        "page_rating_votes": 0,
        "permanent": false,
        "source__id": 175,
        "source_url": "https://kotaku.com/rss",
        "status_code": 0,
        "tags": [],
        "thumbnail": "https://kotaku.com/app/uploads/2025/12/AppleWatch-Series11.jpg",
        "title": "Apple Watch Series 11 Crashes to Record Low to Wind Down Its 2025 Smartwatch Lineup",
        "vote": 0
    },
    {
        "age": null,
        "album": "",
        "author": "Brittany Vincent",
        "bookmarked": false,
        "comments": [],
        "date_created": "2026-01-01T13:34:44.321566+00:00",
        "date_dead_since": null,
        "date_published": "2026-01-01T13:05:00+00:00",
        "description": "<p><img width=\"1500\" height=\"1000\" src=\"https://kotaku.com/app/uploads/2025/12/Anker-Solix-Portable-Power-Station.jpg\" class=\"attachment-full size-full wp-post-image\" alt=\"Anker Solix Portable Power Station\" style=\"max-width: 100%; height: auto; margin: auto;\" decoding=\"async\" fetchpriority=\"high\" srcset=\"https://kotaku.com/app/uploads/2025/12/Anker-Solix-Portable-Power-Station.jpg 1500w, https://kotaku.com/app/uploads/2025/12/Anker-Solix-Portable-Power-Station-336x224.jpg 336w, https://kotaku.com/app/uploads/2025/12/Anker-Solix-Portable-Power-Station-1280x853.jpg 1280w, https://kotaku.com/app/uploads/2025/12/Anker-Solix-Portable-Power-Station-768x512.jpg 768w, https://kotaku.com/app/uploads/2025/12/Anker-Solix-Portable-Power-Station-672x448.jpg 672w, https://kotaku.com/app/uploads/2025/12/Anker-Solix-Portable-Power-Station-960x640.jpg 960w\" sizes=\"(max-width: 1500px) 100vw, 1500px\"></p>\n<p>Save a massive amount of money on this portable power station and always be prepared.</p>\n<p>Th",
        "id": 4449763,
        "language": "en",
        "link": "https://kotaku.com/anker-goes-big-for-2026-with-59-off-power-station-bundle-including-expansion-batteries-and-solar-panels-2000656218",
        "manual_status_code": 0,
        "page_rating": 32,
        "page_rating_contents": 100,
        "page_rating_visits": 0,
        "page_rating_votes": 0,
        "permanent": false,
        "source__id": 175,
        "source_url": "https://kotaku.com/rss",
        "status_code": 0,
        "tags": [],
        "thumbnail": "https://kotaku.com/app/uploads/2025/12/Anker-Solix-Portable-Power-Station.jpg",
        "title": "Anker Goes Big for 2026 With 59% Off Power Station Bundle Including Expansion Batteries and Solar Panels",
        "vote": 0
    },
    {
        "age": null,
        "album": "",
        "author": "Zainab Falak",
        "bookmarked": false,
        "comments": [],
        "date_created": "2026-01-01T12:27:44.010385+00:00",
        "date_dead_since": null,
        "date_published": "2026-01-01T12:05:44+00:00",
        "description": "<p><img width=\"1500\" height=\"1000\" src=\"https://kotaku.com/app/uploads/2025/12/bose-soundlink.jpg\" class=\"attachment-full size-full wp-post-image\" alt=\"Bose Soundlink\" style=\"max-width: 100%; height: auto; margin: auto;\" decoding=\"async\" fetchpriority=\"high\" srcset=\"https://kotaku.com/app/uploads/2025/12/bose-soundlink.jpg 1500w, https://kotaku.com/app/uploads/2025/12/bose-soundlink-336x224.jpg 336w, https://kotaku.com/app/uploads/2025/12/bose-soundlink-1280x853.jpg 1280w, https://kotaku.com/app/uploads/2025/12/bose-soundlink-768x512.jpg 768w, https://kotaku.com/app/uploads/2025/12/bose-soundlink-672x448.jpg 672w, https://kotaku.com/app/uploads/2025/12/bose-soundlink-960x640.jpg 960w\" sizes=\"(max-width: 1500px) 100vw, 1500px\"></p>\n<p>This speaker fills the room with rich, deep audio, plus exceptional bass.</p>\n<p>The post <a href=\"https://kotaku.com/bose-restocks-the-soundlink-revolve-series-ii-speaker-at-all-time-low-to-start-2026-after-year-end-clearance-2000654996\">Bose Restocks th",
        "id": 4449451,
        "language": "en",
        "link": "https://kotaku.com/bose-restocks-the-soundlink-revolve-series-ii-speaker-at-all-time-low-to-start-2026-after-year-end-clearance-2000654996",
        "manual_status_code": 0,
        "page_rating": 32,
        "page_rating_contents": 100,
        "page_rating_visits": 0,
        "page_rating_votes": 0,
        "permanent": false,
        "source__id": 175,
        "source_url": "https://kotaku.com/rss",
        "status_code": 0,
        "tags": [],
        "thumbnail": "https://kotaku.com/app/uploads/2025/12/bose-soundlink.jpg",
        "title": "Bose Restocks the SoundLink Revolve+ (Series II) Speaker at All-Time Low to Start 2026 After Year-End Clearance",
        "vote": 0
    }
]