[
    {
        "age": null,
        "album": "",
        "author": "CBR",
        "bookmarked": false,
        "comments": [],
        "date_created": "2026-01-03T14:58:19.047674+00:00",
        "date_dead_since": null,
        "date_published": "2026-01-03T14:15:04+00:00",
        "description": "Absolute Batman breaks Batman down to his core DNA, then rebuilds him with almost nothing \u201csacred\u201d except what makes him Batman at a character level. \n\nIn this Heroes Journey Podcast clip, Scott Snyder explains the thesis that means Absolute Batman can strip away the familiar \u201ccomfort features\u201d: no wealth requirement, no cave requirement, and even the idea that Alfred or Robins are essential. \n\nThe goal is a more intense underdog Batman (one kids can relate to) shaped by the fears today\u2019s generation actually lives with, and with a Gotham power structure that makes \u201cbillionaire antagonists\u201d feel plausible.\n\nBatman exists to make you brave in the face of what you fear.\n\nChapters:\n00:08 \u2013 Absolute Batman\u2019s \u201cburn it down\u201d thesis\n01:02 \u2013 Batman\u2019s core: trauma into change\n03:34 \u2013 Writing Batman for today\u2019s kids\n07:47 \u2013 The important photo that becomes the \u201ctotem\u201d\n09:10 \u2013 The big arc: Batman can\u2019t do it alone\n12:25 \u2013 Blockbuster fun, but built around justice\n\n\ud83c\udf99\ufe0f Clip from CBR\u2019s Heroes Journe",
        "id": 4463965,
        "language": "en",
        "link": "https://www.youtube.com/watch?v=ODO4ghH_zro",
        "manual_status_code": 0,
        "page_rating": 27,
        "page_rating_contents": 86,
        "page_rating_visits": 0,
        "page_rating_votes": 0,
        "permanent": false,
        "source__id": 872,
        "source_url": "https://youtube.com/channel/UCuCk_7b2_4uSr6y5hFmjuMQ",
        "status_code": 0,
        "tags": [],
        "thumbnail": "https://i4.ytimg.com/vi/ODO4ghH_zro/hqdefault.jpg",
        "title": "Batman Explained: Absolute Batman's Core Rebuild (w/ Scott Snyder)",
        "vote": 0
    }
]