[
    {
        "age": null,
        "album": "",
        "author": "Will Jones",
        "bookmarked": false,
        "comments": [],
        "date_created": "2026-01-08T19:34:23.839313+00:00",
        "date_dead_since": null,
        "date_published": "2026-01-08T19:00:00+00:00",
        "description": "<p>A trans 'woman' has been accused of a \u00a3100,000 blackmail plot to firebomb a law firm, a court has heard.</p>\n<p>The post <a href=\"https://dailysceptic.org/2026/01/08/trans-woman-threatened-to-firebomb-law-firm-court-hears/\">Trans &#8216;Woman&#8217; &#8220;Threatened to Firebomb Law Firm&#8221;, Court Hears</a> appeared first on <a href=\"https://dailysceptic.org\">The Daily Sceptic</a>.</p>",
        "id": 4509318,
        "language": "en-US",
        "link": "https://dailysceptic.org/2026/01/08/trans-woman-threatened-to-firebomb-law-firm-court-hears",
        "manual_status_code": 0,
        "page_rating": 30,
        "page_rating_contents": 95,
        "page_rating_visits": 0,
        "page_rating_votes": 0,
        "permanent": false,
        "source__id": 89,
        "source_url": "https://dailysceptic.org/feed",
        "status_code": 0,
        "tags": [],
        "thumbnail": null,
        "title": "Trans \u2018Woman\u2019 \u201cThreatened to Firebomb Law Firm\u201d, Court Hears",
        "vote": 0
    },
    {
        "age": null,
        "album": "",
        "author": "Will Jones",
        "bookmarked": false,
        "comments": [],
        "date_created": "2026-01-08T17:14:05.322346+00:00",
        "date_dead_since": null,
        "date_published": "2026-01-08T17:00:00+00:00",
        "description": "<p>The \"abusive behaviour\" of migrants staying in a local hotel and the \"ongoing damage\" they are causing has been blamed for the closure of a 20 year-old restaurant.</p>\n<p>The post <a href=\"https://dailysceptic.org/2026/01/08/hotel-migrants-abusive-behaviour-forces-restaurant-to-close/\">Hotel Migrants&#8217; &#8220;Abusive Behaviour&#8221; Forces Restaurant to Close</a> appeared first on <a href=\"https://dailysceptic.org\">The Daily Sceptic</a>.</p>",
        "id": 4507957,
        "language": "en-US",
        "link": "https://dailysceptic.org/2026/01/08/hotel-migrants-abusive-behaviour-forces-restaurant-to-close",
        "manual_status_code": 0,
        "page_rating": 30,
        "page_rating_contents": 95,
        "page_rating_visits": 0,
        "page_rating_votes": 0,
        "permanent": false,
        "source__id": 89,
        "source_url": "https://dailysceptic.org/feed",
        "status_code": 0,
        "tags": [],
        "thumbnail": null,
        "title": "Hotel Migrants\u2019 \u201cAbusive Behaviour\u201d Forces Restaurant to Close",
        "vote": 0
    },
    {
        "age": null,
        "album": "",
        "author": "James Alexander",
        "bookmarked": false,
        "comments": [],
        "date_created": "2026-01-08T15:01:23.860724+00:00",
        "date_dead_since": null,
        "date_published": "2026-01-08T15:00:00+00:00",
        "description": "<p>Great Powers are currently engaged in dangerous brinkmanship to test the balance of their power. It would be better, argues Professor James Alexander, if they rediscovered the value of restraint.</p>\n<p>The post <a href=\"https://dailysceptic.org/2026/01/08/the-difference-between-balance-of-power-and-restraint-of-power/\">The Difference Between Balance of Power and Restraint of Power</a> appeared first on <a href=\"https://dailysceptic.org\">The Daily Sceptic</a>.</p>",
        "id": 4506697,
        "language": "en-US",
        "link": "https://dailysceptic.org/2026/01/08/the-difference-between-balance-of-power-and-restraint-of-power",
        "manual_status_code": 0,
        "page_rating": 30,
        "page_rating_contents": 95,
        "page_rating_visits": 0,
        "page_rating_votes": 0,
        "permanent": false,
        "source__id": 89,
        "source_url": "https://dailysceptic.org/feed",
        "status_code": 0,
        "tags": [],
        "thumbnail": null,
        "title": "The Difference Between Balance of Power and Restraint of Power",
        "vote": 0
    },
    {
        "age": null,
        "album": "",
        "author": "Will Jones",
        "bookmarked": false,
        "comments": [],
        "date_created": "2026-01-08T13:54:27.227812+00:00",
        "date_dead_since": null,
        "date_published": "2026-01-08T13:00:00+00:00",
        "description": "<p>Twenty-two Labour councils are poised to postpone local elections, all of them in areas where Reform UK is set to surge. </p>\n<p>The post <a href=\"https://dailysceptic.org/2026/01/08/twenty-two-labour-councils-set-to-delay-local-elections-in-areas-reform-is-predicted-to-surge/\">Twenty-Two Labour Councils Set to Delay Local Elections in Areas Reform is Predicted to Surge</a> appeared first on <a href=\"https://dailysceptic.org\">The Daily Sceptic</a>.</p>",
        "id": 4506096,
        "language": "en-US",
        "link": "https://dailysceptic.org/2026/01/08/twenty-two-labour-councils-set-to-delay-local-elections-in-areas-reform-is-predicted-to-surge",
        "manual_status_code": 0,
        "page_rating": 30,
        "page_rating_contents": 95,
        "page_rating_visits": 0,
        "page_rating_votes": 0,
        "permanent": false,
        "source__id": 89,
        "source_url": "https://dailysceptic.org/feed",
        "status_code": 0,
        "tags": [],
        "thumbnail": null,
        "title": "Twenty-Two Labour Councils Set to Delay Local Elections in Areas Reform is Predicted to Surge",
        "vote": 0
    },
    {
        "age": null,
        "album": "",
        "author": "Will Jones",
        "bookmarked": false,
        "comments": [],
        "date_created": "2026-01-08T11:41:32.252693+00:00",
        "date_dead_since": null,
        "date_published": "2026-01-08T11:00:00+00:00",
        "description": "<p>Britain\u2019s reliance on fossil fuels has increased for the first time in four years, dealing a\u00a0major blow to Ed Miliband's Net Zero hopes of decarbonising the grid by 2030.</p>\n<p>The post <a href=\"https://dailysceptic.org/2026/01/08/britains-surging-reliance-on-gas-deals-fresh-blow-to-net-zero/\">Britain&#8217;s Surging Reliance on Gas Deals Fresh Blow to Miliband Net Zero Hopes</a> appeared first on <a href=\"https://dailysceptic.org\">The Daily Sceptic</a>.</p>",
        "id": 4505134,
        "language": "en-US",
        "link": "https://dailysceptic.org/2026/01/08/britains-surging-reliance-on-gas-deals-fresh-blow-to-net-zero",
        "manual_status_code": 0,
        "page_rating": 30,
        "page_rating_contents": 95,
        "page_rating_visits": 0,
        "page_rating_votes": 0,
        "permanent": false,
        "source__id": 89,
        "source_url": "https://dailysceptic.org/feed",
        "status_code": 0,
        "tags": [],
        "thumbnail": null,
        "title": "Britain\u2019s Surging Reliance on Gas Deals Fresh Blow to Miliband Net Zero Hopes",
        "vote": 0
    },
    {
        "age": null,
        "album": "",
        "author": "Chris Morrison",
        "bookmarked": false,
        "comments": [],
        "date_created": "2026-01-08T09:30:33.627098+00:00",
        "date_dead_since": null,
        "date_published": "2026-01-08T09:00:00+00:00",
        "description": "<p>Global temperature anomalies on both land and sea are dropping like a stone. But you won't hear about this from narrative-captured mainstream media, says Chris Morrison.</p>\n<p>The post <a href=\"https://dailysceptic.org/2026/01/08/dramatic-fall-in-global-temperatures-ignored-by-narrative-captured-mainstream-media/\">Dramatic Fall in Global Temperatures Ignored by Narrative-Captured Mainstream Media</a> appeared first on <a href=\"https://dailysceptic.org\">The Daily Sceptic</a>.</p>",
        "id": 4504340,
        "language": "en-US",
        "link": "https://dailysceptic.org/2026/01/08/dramatic-fall-in-global-temperatures-ignored-by-narrative-captured-mainstream-media",
        "manual_status_code": 0,
        "page_rating": 30,
        "page_rating_contents": 95,
        "page_rating_visits": 0,
        "page_rating_votes": 0,
        "permanent": false,
        "source__id": 89,
        "source_url": "https://dailysceptic.org/feed",
        "status_code": 0,
        "tags": [],
        "thumbnail": null,
        "title": "Dramatic Fall in Global Temperatures Ignored by Narrative-Captured Mainstream Media",
        "vote": 0
    },
    {
        "age": null,
        "album": "",
        "author": "Charlotte Gill",
        "bookmarked": false,
        "comments": [],
        "date_created": "2026-01-08T07:24:16.030357+00:00",
        "date_dead_since": null,
        "date_published": "2026-01-08T07:00:00+00:00",
        "description": "<p>Charlotte Gill exposes the hundreds of millions of pounds of taxpayers' money being given to migrant charities \u2013 including organisations that help migrants jump the housing queue ahead of homeless Brits.</p>\n<p>The post <a href=\"https://dailysceptic.org/2026/01/08/the-enormous-amounts-of-taxpayer-funding-going-to-migrant-charities/\">The Enormous Amounts of Taxpayer Funding Going to Migrant Charities</a> appeared first on <a href=\"https://dailysceptic.org\">The Daily Sceptic</a>.</p>",
        "id": 4503748,
        "language": "en-US",
        "link": "https://dailysceptic.org/2026/01/08/the-enormous-amounts-of-taxpayer-funding-going-to-migrant-charities",
        "manual_status_code": 0,
        "page_rating": 30,
        "page_rating_contents": 95,
        "page_rating_visits": 0,
        "page_rating_votes": 0,
        "permanent": false,
        "source__id": 89,
        "source_url": "https://dailysceptic.org/feed",
        "status_code": 0,
        "tags": [],
        "thumbnail": null,
        "title": "The Enormous Amounts of Taxpayer Funding Going to Migrant Charities",
        "vote": 0
    },
    {
        "age": null,
        "album": "",
        "author": "Richard Eldred",
        "bookmarked": false,
        "comments": [],
        "date_created": "2026-01-08T01:57:12.835221+00:00",
        "date_dead_since": null,
        "date_published": "2026-01-08T01:02:24+00:00",
        "description": "<p>A summary of the most interesting stories in the past 24 hours that challenge the prevailing orthodoxy about the \u2018climate emergency\u2019, public health \u2018crises\u2019 and the supposed moral defects of Western civilisation.</p>\n<p>The post <a href=\"https://dailysceptic.org/2026/01/08/news-round-up-1759/\">News Round-Up</a> appeared first on <a href=\"https://dailysceptic.org\">The Daily Sceptic</a>.</p>",
        "id": 4502413,
        "language": "en-US",
        "link": "https://dailysceptic.org/2026/01/08/news-round-up-1759",
        "manual_status_code": 0,
        "page_rating": 30,
        "page_rating_contents": 95,
        "page_rating_visits": 0,
        "page_rating_votes": 0,
        "permanent": false,
        "source__id": 89,
        "source_url": "https://dailysceptic.org/feed",
        "status_code": 0,
        "tags": [],
        "thumbnail": null,
        "title": "News Round-Up",
        "vote": 0
    }
]