[
    {
        "age": null,
        "album": "",
        "author": "SAMTIME",
        "bookmarked": false,
        "comments": [],
        "date_created": "2026-01-05T18:26:09.185381+00:00",
        "date_dead_since": null,
        "date_published": "2026-01-05T17:30:31+00:00",
        "description": "The PS5 Boot ROM keys have leaked online which brings hackers one step closer to jailbreaking the console and Sony one step closer to crapping their pants.\n\nARTICLE: https://www.tomshardware.com/video-games/playstation/playstation-5-rom-keys-leaked-jailbreaking-could-be-made-easier-with-bootrom-codes\n\nSUPPORT: https://funkytime.tv/patriot-signup/\nMERCH: https://funkytime.tv/shop/\nFUNKY TIME WEBSITE: https://funkytime.tv\n\nFACEBOOK: http://www.facebook.com/SamtimeNews\nTWITTER: http://twitter.com/SamtimeNews\nINSTAGRAM: http://instagram.com/samtimenews\n\n#PS5 #Jailbreak\n\n-----------------------------------\n\n'Escape the ordinary. Embrace the FUNKY!'\n\n-----------------------------------\n\nSAMTIME is a parody channel and does not represent the tech company featured.\n\nFor sponsorship enquiries: samtime@bossmgmtgrp.com\nFor other business enquiries: business@funkytime.tv\nCopyright FUNKY TIME PRODUCTIONS 2025",
        "id": 4479593,
        "language": "en-US",
        "link": "https://www.youtube.com/watch?v=yTJXJ_AUgnc",
        "manual_status_code": 0,
        "page_rating": 27,
        "page_rating_contents": 86,
        "page_rating_visits": 1,
        "page_rating_votes": 0,
        "permanent": false,
        "source__id": 290,
        "source_url": "https://www.youtube.com/feeds/videos.xml?channel_id=UCd6vEDS3SOhWbXZrxbrf_bw",
        "status_code": 0,
        "tags": [],
        "thumbnail": "https://i2.ytimg.com/vi/yTJXJ_AUgnc/hqdefault.jpg",
        "title": "Sony Reacts to Unfixable PS5 Jailbreak Leak",
        "vote": 0
    }
]