[
    {
        "age": null,
        "album": "",
        "author": "Louis Rossmann",
        "bookmarked": false,
        "comments": [],
        "date_created": "2026-01-10T04:19:31.647983+00:00",
        "date_dead_since": null,
        "date_published": "2026-01-10T03:16:39+00:00",
        "description": "https://gothamist.com/news/nyc-wegmans-is-storing-biometric-data-on-shoppers-eyes-voices-and-faces\n\nhttps://web.archive.org/web/20250120131517/https://rossmanngroup.com/dca-license-number-citations-not-feeling-like-much-of-a-cultivated-garden-right-now/\n\nhttps://alpr.watch/\n\nhttps://www.youtube.com/playlist?list=PLkVbIsAWN2lvzWirQsz6haGEjJ2b2e6Ho\n\nhttps://www.youtube.com/playlist?list=PLkVbIsAWN2ls-WXrvFtAxoJ_VZIMSG9Z3",
        "id": 4521667,
        "language": "en-US",
        "link": "https://www.youtube.com/watch?v=ZfPGPFyFrrg",
        "manual_status_code": 0,
        "page_rating": 27,
        "page_rating_contents": 86,
        "page_rating_visits": 0,
        "page_rating_votes": 0,
        "permanent": false,
        "source__id": 201,
        "source_url": "https://www.youtube.com/feeds/videos.xml?channel_id=UCl2mFZoRqjw_ELax4Yisf6w",
        "status_code": 0,
        "tags": [],
        "thumbnail": "https://i3.ytimg.com/vi/ZfPGPFyFrrg/hqdefault.jpg",
        "title": "Wegman's biometric data collection and a general NYC rant",
        "vote": 0
    },
    {
        "age": null,
        "album": "",
        "author": "Louis Rossmann",
        "bookmarked": false,
        "comments": [],
        "date_created": "2026-01-10T02:01:34.549018+00:00",
        "date_dead_since": null,
        "date_published": "2026-01-10T01:20:56+00:00",
        "description": "https://consumerrights.wiki/w/Bose_kills_SoundTouch_and_speakers_lose_smart_functionality#cite_note-8\nhttps://www.youtube.com/watch?v=IHYfBtmei3o\nhttps://www.bose.com/soundtouch-end-of-life\nhttps://assets.bosecreative.com/m/496577402d128874/original/SoundTouch-Web-API.pdf",
        "id": 4521187,
        "language": "en-US",
        "link": "https://www.youtube.com/watch?v=NojFSQIGfkI",
        "manual_status_code": 0,
        "page_rating": 27,
        "page_rating_contents": 86,
        "page_rating_visits": 0,
        "page_rating_votes": 0,
        "permanent": false,
        "source__id": 201,
        "source_url": "https://www.youtube.com/feeds/videos.xml?channel_id=UCl2mFZoRqjw_ELax4Yisf6w",
        "status_code": 0,
        "tags": [],
        "thumbnail": "https://i3.ytimg.com/vi/NojFSQIGfkI/hqdefault.jpg",
        "title": "Bose employees deserve a big thank you for respecting ownership!",
        "vote": 0
    }
]